{"WLDunaway": {"tweets": 51, "followers": 33}, "valerie_torrlo": {"tweets": 4675, "followers": 126}, "SattamAltaweel": {"tweets": 9303, "followers": 335}, "janeMOOrrison": {"tweets": 1622, "followers": 355}, "morgcour": {"tweets": 40, "followers": 17}, "Ndenges_1": {"tweets": 290, "followers": 153}, "medihab": {"tweets": 881, "followers": 133}, "Enqifakebrown": {"tweets": 2987, "followers": 149}, "xunholyx": {"tweets": 278, "followers": 235}, "Ben_Greenwood": {"tweets": 8009, "followers": 1669}, "TheRealMrAdams": {"tweets": 17582, "followers": 452}, "crackerhankins": {"tweets": 1092, "followers": 135}, "bimbisara": {"tweets": 169, "followers": 50}, "ca_ormastroniBJ": {"tweets": 4647, "followers": 365}, "danieldd66": {"tweets": 66, "followers": 19}, "CarlClements4": {"tweets": 486, "followers": 114}, "karlgroves98": {"tweets": 53, "followers": 147}, "chelleatlarge": {"tweets": 1210, "followers": 61}, "JMInspirations": {"tweets": 1213, "followers": 297}, "hjordor": {"tweets": 268, "followers": 163}, "pknightmiller": {"tweets": 95, "followers": 38}, "Honeymaid": {"tweets": 2897, "followers": 518}, "LouHayman": {"tweets": 401, "followers": 67}, "asysteminc": {"tweets": 1925, "followers": 3624}, "Willibc13": {"tweets": 745, "followers": 54}, "FisherStudio": {"tweets": 382, "followers": 82}, "63_sa": {"tweets": 32, "followers": 68}, "NewbyBachmeier": {"tweets": 324, "followers": 207}, "CapMalcolm": {"tweets": 4607, "followers": 1244}, "fluidmotionecm": {"tweets": 225, "followers": 13}, "Naaja_Darwin": {"tweets": 474, "followers": 1476}, "kawa2zero": {"tweets": 52, "followers": 64}, "BAtTheNile": {"tweets": 2102, "followers": 216}, "luisperfeto": {"tweets": 743, "followers": 199}, "serrywood": {"tweets": 23517, "followers": 4879}, "Artemis17H": {"tweets": 7074, "followers": 348}, "thedogpunt": {"tweets": 77, "followers": 187}, "BarigyeKenneth": {"tweets": 42, "followers": 12}, "ShaanJoshi": {"tweets": 715, "followers": 1209}, "eckert_lena": {"tweets": 3260, "followers": 196}, "piosneer": {"tweets": 30907, "followers": 978}, "alcolera": {"tweets": 467, "followers": 44}, "erickjaviervarg": {"tweets": 32, "followers": 11}, "_iamkyshawn": {"tweets": 55, "followers": 375}, "kettbauer": {"tweets": 23622, "followers": 444}, "SardImperium": {"tweets": 9782, "followers": 418}, "YvngDs": {"tweets": 301, "followers": 139}, "lreichenstein": {"tweets": 417, "followers": 23}, "Atreyu2183": {"tweets": 926, "followers": 203}, "SassyPlayz": {"tweets": 42, "followers": 15}}